odoo/addons/base_partner_merge/README.rst
odoo/addons/base_partner_merge/__init__.py
odoo/addons/base_partner_merge/__manifest__.py
odoo/addons/base_partner_merge/i18n/am.po
odoo/addons/base_partner_merge/i18n/am_ET.po
odoo/addons/base_partner_merge/i18n/ar.po
odoo/addons/base_partner_merge/i18n/ar_SY.po
odoo/addons/base_partner_merge/i18n/base_partner_merge.pot
odoo/addons/base_partner_merge/i18n/bg.po
odoo/addons/base_partner_merge/i18n/bs.po
odoo/addons/base_partner_merge/i18n/bs_BA.po
odoo/addons/base_partner_merge/i18n/ca.po
odoo/addons/base_partner_merge/i18n/ca_ES.po
odoo/addons/base_partner_merge/i18n/cs.po
odoo/addons/base_partner_merge/i18n/cs_CZ.po
odoo/addons/base_partner_merge/i18n/da.po
odoo/addons/base_partner_merge/i18n/da_DK.po
odoo/addons/base_partner_merge/i18n/de.po
odoo/addons/base_partner_merge/i18n/de_CH.po
odoo/addons/base_partner_merge/i18n/el_GR.po
odoo/addons/base_partner_merge/i18n/en_GB.po
odoo/addons/base_partner_merge/i18n/es.po
odoo/addons/base_partner_merge/i18n/es_AR.po
odoo/addons/base_partner_merge/i18n/es_CL.po
odoo/addons/base_partner_merge/i18n/es_CO.po
odoo/addons/base_partner_merge/i18n/es_CR.po
odoo/addons/base_partner_merge/i18n/es_DO.po
odoo/addons/base_partner_merge/i18n/es_EC.po
odoo/addons/base_partner_merge/i18n/es_ES.po
odoo/addons/base_partner_merge/i18n/es_GT.po
odoo/addons/base_partner_merge/i18n/es_MX.po
odoo/addons/base_partner_merge/i18n/es_PE.po
odoo/addons/base_partner_merge/i18n/es_PY.po
odoo/addons/base_partner_merge/i18n/es_VE.po
odoo/addons/base_partner_merge/i18n/et.po
odoo/addons/base_partner_merge/i18n/et_EE.po
odoo/addons/base_partner_merge/i18n/eu.po
odoo/addons/base_partner_merge/i18n/eu_ES.po
odoo/addons/base_partner_merge/i18n/fa.po
odoo/addons/base_partner_merge/i18n/fa_IR.po
odoo/addons/base_partner_merge/i18n/fi.po
odoo/addons/base_partner_merge/i18n/fr.po
odoo/addons/base_partner_merge/i18n/fr_CA.po
odoo/addons/base_partner_merge/i18n/fr_CH.po
odoo/addons/base_partner_merge/i18n/gl.po
odoo11_addon_base_partner_merge-11.0.1.0.1.99.dev7.dist-info/METADATA
odoo11_addon_base_partner_merge-11.0.1.0.1.99.dev7.dist-info/WHEEL
odoo11_addon_base_partner_merge-11.0.1.0.1.99.dev7.dist-info/top_level.txt
odoo11_addon_base_partner_merge-11.0.1.0.1.99.dev7.dist-info/RECORD
